<?xml version="1.0" encoding="utf-8"?>
<EntityRelationships xmlns:xsi="http://www.w3.org/2001/XMLSchema-instance">
  <EntityRelationship Name="komet_avis_team_owningteam">
    <EntityRelationshipType>OneToMany</EntityRelationshipType>
    <IsCustomizable>1</IsCustomizable>
    <IntroducedVersion>1.0.0.0</IntroducedVersion>
    <IsHierarchical>0</IsHierarchical>
    <ReferencingEntityName>komet_avis</ReferencingEntityName>
    <ReferencedEntityName>Team</ReferencedEntityName>
    <CascadeAssign>NoCascade</CascadeAssign>
    <CascadeDelete>NoCascade</CascadeDelete>
    <CascadeArchive>NoCascade</CascadeArchive>
    <CascadeReparent>NoCascade</CascadeReparent>
    <CascadeShare>NoCascade</CascadeShare>
    <CascadeUnshare>NoCascade</CascadeUnshare>
    <CascadeRollupView>NoCascade</CascadeRollupView>
    <ReferencingAttributeName>OwningTeam</ReferencingAttributeName>
    <RelationshipDescription>
      <Descriptions>
        <Description description="Eindeutiger Bezeichner des Teams, das im Besitz der Aktivität ist." languagecode="1031" />
      </Descriptions>
    </RelationshipDescription>
  </EntityRelationship>
  <EntityRelationship Name="team_komet_avistemplate">
    <EntityRelationshipType>OneToMany</EntityRelationshipType>
    <IsCustomizable>1</IsCustomizable>
    <IntroducedVersion>1.0</IntroducedVersion>
    <IsHierarchical>0</IsHierarchical>
    <ReferencingEntityName>komet_avistemplate</ReferencingEntityName>
    <ReferencedEntityName>Team</ReferencedEntityName>
    <CascadeAssign>NoCascade</CascadeAssign>
    <CascadeDelete>NoCascade</CascadeDelete>
    <CascadeArchive>NoCascade</CascadeArchive>
    <CascadeReparent>NoCascade</CascadeReparent>
    <CascadeShare>NoCascade</CascadeShare>
    <CascadeUnshare>NoCascade</CascadeUnshare>
    <ReferencingAttributeName>OwningTeam</ReferencingAttributeName>
    <RelationshipDescription>
      <Descriptions>
        <Description description="Eindeutiger Bezeichner des für den Datensatz zuständigen Teams." languagecode="1031" />
      </Descriptions>
    </RelationshipDescription>
  </EntityRelationship>
</EntityRelationships>